monarch_gene_mapping/__init__.py
monarch_gene_mapping/cli_utils.py
monarch_gene_mapping/download.yaml
monarch_gene_mapping/main.py
monarch_gene_mapping/uniprot_idmapping_preprocess.py
monarch_gene_mapping-0.1.7.dist-info/METADATA
monarch_gene_mapping-0.1.7.dist-info/WHEEL
monarch_gene_mapping-0.1.7.dist-info/entry_points.txt
monarch_gene_mapping-0.1.7.dist-info/RECORD
