Metadata-Version: 2.1
Name: monarch_gene_mapping
Version: 0.1.7
Summary: Project for mapping source namespaces to preffered namespaces in Monarch Initiative
Author: Tim Putman
Author-email: putmantime@users.noreply.github.com
Requires-Python: >=3.9,<4.0
Classifier: Programming Language :: Python :: 3
Classifier: Programming Language :: Python :: 3.9
Classifier: Programming Language :: Python :: 3.10
Classifier: Programming Language :: Python :: 3.11
Classifier: Programming Language :: Python :: 3.12
Requires-Dist: kghub-downloader (>=0.3.4,<0.4.0)
Requires-Dist: pandas (>=2.1.3,<3.0.0)
Requires-Dist: typer (>=0.7,<0.8)
